filtercss/__init__.py
filtercss-0.0.2.dist-info/LICENSE.md
filtercss-0.0.2.dist-info/METADATA
filtercss-0.0.2.dist-info/WHEEL
filtercss-0.0.2.dist-info/top_level.txt
filtercss-0.0.2.dist-info/RECORD
