Metadata-Version: 2.1
Name: filtercss
Version: 0.0.2
Summary: Tool for filtering unused CSS.
Home-page: https://github.com/J08nY/filtercss/
Author: Jan Jancar
Author-email: johny@neuromancer.sk
License: MIT
Platform: UNKNOWN
Requires-Python: >=3.8
License-File: LICENSE.md
Requires-Dist: tinycss2
Requires-Dist: beautifulsoup4
Requires-Dist: lxml
